LICENSE.txt
MANIFEST.in
README.md
setup.cfg
setup.py
opencc/NOTICE.txt
opencc/README.md
opencc/__init__.py
opencc/__main__.py
opencc/opencc.py
opencc/config/hk2s.json
opencc/config/s2hk.json
opencc/config/s2t.json
opencc/config/s2tw.json
opencc/config/s2twp.json
opencc/config/t2hk.json
opencc/config/t2s.json
opencc/config/t2tw.json
opencc/config/tw2s.json
opencc/config/tw2sp.json
opencc/dictionary/HKVariants.txt
opencc/dictionary/HKVariantsPhrases.txt
opencc/dictionary/HKVariantsRev.txt
opencc/dictionary/HKVariantsRevPhrases.txt
opencc/dictionary/JPShinjitaiCharacters.txt
opencc/dictionary/JPShinjitaiPhrases.txt
opencc/dictionary/JPVariants.txt
opencc/dictionary/JPVariantsRev.txt
opencc/dictionary/STCharacters.txt
opencc/dictionary/STPhrases.txt
opencc/dictionary/TSCharacters.txt
opencc/dictionary/TSPhrases.txt
opencc/dictionary/TWPhrases.txt
opencc/dictionary/TWPhrasesIT.txt
opencc/dictionary/TWPhrasesName.txt
opencc/dictionary/TWPhrasesOther.txt
opencc/dictionary/TWPhrasesRev.txt
opencc/dictionary/TWVariants.txt
opencc/dictionary/TWVariantsRev.txt
opencc/dictionary/TWVariantsRevPhrases.txt
opencc_python_reimplemented.egg-info/PKG-INFO
opencc_python_reimplemented.egg-info/SOURCES.txt
opencc_python_reimplemented.egg-info/dependency_links.txt
opencc_python_reimplemented.egg-info/top_level.txt